mdcraft/__init__.py
mdcraft/algorithm/__init__.py
mdcraft/algorithm/accelerated.py
mdcraft/algorithm/correlation.py
mdcraft/algorithm/molecule.py
mdcraft/algorithm/topology.py
mdcraft/algorithm/unit.py
mdcraft/algorithm/utility.py
mdcraft/analysis/__init__.py
mdcraft/analysis/base.py
mdcraft/analysis/electrostatics.py
mdcraft/analysis/polymer.py
mdcraft/analysis/profile.py
mdcraft/analysis/reader.py
mdcraft/analysis/structure.py
mdcraft/analysis/thermodynamics.py
mdcraft/analysis/transport.py
mdcraft/fit/__init__.py
mdcraft/fit/distribution.py
mdcraft/fit/exponential.py
mdcraft/fit/fourier.py
mdcraft/fit/gaussian.py
mdcraft/fit/polynomial.py
mdcraft/fit/power.py
mdcraft/lammps/__init__.py
mdcraft/lammps/topology.py
mdcraft/openmm/__init__.py
mdcraft/openmm/bond.py
mdcraft/openmm/file.py
mdcraft/openmm/pair.py
mdcraft/openmm/reporter.py
mdcraft/openmm/system.py
mdcraft/openmm/topology.py
mdcraft/openmm/unit.py
mdcraft/openmm/utility.py
mdcraft/plot/__init__.py
mdcraft/plot/axis.py
mdcraft/plot/color.py
mdcraft/plot/rcparam.py
mdcraft-1.3.2.dist-info/LICENSE
mdcraft-1.3.2.dist-info/METADATA
mdcraft-1.3.2.dist-info/WHEEL
mdcraft-1.3.2.dist-info/top_level.txt
mdcraft-1.3.2.dist-info/RECORD
