Metadata-Version: 2.2
Name: mdcraft
Version: 1.3.2
Author-email: "Benjamin B. Ye" <bye@caltech.edu>, "Pierre J. Walker" <pjwalker@caltech.edu>
License:                     GNU GENERAL PUBLIC LICENSE
Project-URL: Homepage, https://github.com/bbye98/mdcraft
Project-URL: Bug Tracker, https://github.com/bbye98/mdcraft/issues
Classifier: Intended Audience :: Science/Research
Classifier: License :: OSI Approved :: GNU General Public License v3 or later (GPLv3+)
Classifier: Operating System :: OS Independent
Classifier: Programming Language :: Python
Classifier: Programming Language :: Python :: 3
Requires-Python: >=3.9
License-File: LICENSE
Requires-Dist: matplotlib
Requires-Dist: mdanalysis
Requires-Dist: netCDF4
Requires-Dist: numba
Requires-Dist: numpy
Requires-Dist: pandas
Requires-Dist: pint
Requires-Dist: psutil
Requires-Dist: scipy
Requires-Dist: sympy
